{
  "/_app": "pages/_app.js",
  "/_document": "pages/_document.js",
  "/about": "pages/about.html",
  "/api/portfolio/[slug]": "pages/api/portfolio/[slug].js",
  "/api/portfolio": "pages/api/portfolio.js",
  "/blog-card-2": "pages/blog-card-2.html",
  "/blog-card-3": "pages/blog-card-3.html",
  "/blog-card": "pages/blog-card.html",
  "/blog-classic-2": "pages/blog-classic-2.html",
  "/blog-classic-3": "pages/blog-classic-3.html",
  "/blog-classic": "pages/blog-classic.html",
  "/blog-list-2": "pages/blog-list-2.html",
  "/blog-list": "pages/blog-list.html",
  "/carousel-portfolio-1": "pages/carousel-portfolio-1.html",
  "/carousel-portfolio-2": "pages/carousel-portfolio-2.html",
  "/carousel-portfolio-3": "pages/carousel-portfolio-3.html",
  "/contact": "pages/contact.html",
  "/corporate-2": "pages/corporate-2.html",
  "/corporate": "pages/corporate.html",
  "/demo-2": "pages/demo-2.html",
  "/demo-3": "pages/demo-3.html",
  "/imprint": "pages/imprint.html",
  "/_error": "pages/_error.js",
  "/": "pages/index.html",
  "/personal-2": "pages/personal-2.html",
  "/personal": "pages/personal.html",
  "/portfolio/lufthansa": "pages/portfolio/lufthansa.html",
  "/portfolio/bmw-group": "pages/portfolio/bmw-group.html",
  "/portfolio/mercedes-benz": "pages/portfolio/mercedes-benz.html",
  "/portfolio/thyssenkrupp": "pages/portfolio/thyssenkrupp.html",
  "/service": "pages/service.html",
  "/single-blog": "pages/single-blog.html",
  "/slider-full-distortion-v": "pages/slider-full-distortion-v.html",
  "/slider-full-distortion-h": "pages/slider-full-distortion-h.html",
  "/slider-full-parallax-h": "pages/slider-full-parallax-h.html",
  "/slider-full-parallax-v": "pages/slider-full-parallax-v.html",
  "/slider-half-distortion-h": "pages/slider-half-distortion-h.html",
  "/slider-half-distortion-v": "pages/slider-half-distortion-v.html",
  "/slider-half-parallax-h": "pages/slider-half-parallax-h.html",
  "/slider-half-parallax-v": "pages/slider-half-parallax-v.html",
  "/slider-padding-distortion-h": "pages/slider-padding-distortion-h.html",
  "/slider-padding-distortion-v": "pages/slider-padding-distortion-v.html",
  "/slider-padding-parallax-h": "pages/slider-padding-parallax-h.html",
  "/slider-padding-parallax-v": "pages/slider-padding-parallax-v.html",
  "/work-card-2-col": "pages/work-card-2-col.html",
  "/work-card-3-col": "pages/work-card-3-col.html",
  "/work-card-4-col": "pages/work-card-4-col.html",
  "/work-classic-2-col": "pages/work-classic-2-col.html",
  "/work-classic": "pages/work-classic.html",
  "/404": "pages/404.html"
}